vars_gridview/__init__.py
vars_gridview/__main__.py
vars_gridview/assets/gridview.ui
vars_gridview/assets/icons/README.md
vars_gridview/assets/icons/VARSGridView.icns
vars_gridview/assets/icons/checkmark.png
vars_gridview/assets/icons/folder-open-solid.svg
vars_gridview/assets/icons/gear-solid.svg
vars_gridview/assets/icons/left-long-solid.svg
vars_gridview/assets/icons/magnifying-glass-solid.svg
vars_gridview/assets/icons/right-long-solid.svg
vars_gridview/assets/icons/VARSGridView.iconset/icon_128.png
vars_gridview/assets/icons/VARSGridView.iconset/icon_16.png
vars_gridview/assets/icons/VARSGridView.iconset/icon_256.png
vars_gridview/assets/icons/VARSGridView.iconset/icon_32.png
vars_gridview/assets/icons/VARSGridView.iconset/icon_512.png
vars_gridview/assets/style/dark.qss
vars_gridview/lib/__init__.py
vars_gridview/lib/association.py
vars_gridview/lib/box_handler.py
vars_gridview/lib/constants.py
vars_gridview/lib/embedding.py
vars_gridview/lib/log.py
vars_gridview/lib/observation.py
vars_gridview/lib/raziel.py
vars_gridview/lib/runnables.py
vars_gridview/lib/settings.py
vars_gridview/lib/sort_methods.py
vars_gridview/lib/utils.py
vars_gridview/lib/m3/__init__.py
vars_gridview/lib/m3/clients.py
vars_gridview/lib/m3/operations.py
vars_gridview/lib/m3/query.py
vars_gridview/ui/BoundingBox.py
vars_gridview/ui/CentralWidget.py
vars_gridview/ui/ConceptSelectionDialog.py
vars_gridview/ui/ConfirmationDialog.py
vars_gridview/ui/ControlBar.py
vars_gridview/ui/FileSelectionLineEdit.py
vars_gridview/ui/ImageMosaic.py
vars_gridview/ui/InfoPanel.py
vars_gridview/ui/JSONTree.py
vars_gridview/ui/LoginDialog.py
vars_gridview/ui/MainWindow.py
vars_gridview/ui/QueryDialog.py
vars_gridview/ui/RectWidget.py
vars_gridview/ui/RoiGraphicsView.py
vars_gridview/ui/SortDialog.py
vars_gridview/ui/StatusInfoItem.py
vars_gridview/ui/StatusInfoWidget.py
vars_gridview/ui/__init__.py
vars_gridview/ui/settings/SettingsDialog.py
vars_gridview/ui/settings/__init__.py
vars_gridview-0.29.0.dist-info/METADATA
vars_gridview-0.29.0.dist-info/WHEEL
vars_gridview-0.29.0.dist-info/entry_points.txt
vars_gridview-0.29.0.dist-info/licenses/LICENSE
vars_gridview-0.29.0.dist-info/RECORD
