Metadata-Version: 2.4
Name: vars-gridview
Version: 0.29.0
Summary: VARS GridView is a tool for reviewing and correcting VARS localizations in bulk.
Author-email: Kevin Barnard <kbarnard@mbari.org>, Paul Roberts <proberts@mbari.org>
License-Expression: MIT
License-File: LICENSE
Keywords: VARS,annotation,localization
Requires-Python: >=3.9
Requires-Dist: beholder-client>=0.3.1
Requires-Dist: cachetools>=5.5.1
Requires-Dist: dreamsim>=0.1.3
Requires-Dist: iso8601>=2.1.0
Requires-Dist: opencv-python>=4.5.5.62
Requires-Dist: platformdirs>=4.0.0
Requires-Dist: pydantic>=2.10.6
Requires-Dist: pyqt6>=6.4.0
Requires-Dist: pyqtgraph>=0.13.0
Requires-Dist: qdarkstyle>=3.0.3
Requires-Dist: requests>=2.27.1
Requires-Dist: sharktopoda-client>=0.4.5
